Metadata-Version: 2.1
Name: clista
Version: 0.0.2
Summary: Create interactive web app from any CLI with streamlit
Home-page: https://github.com/hvnsweeting/clista
Author: Viet Hung Nguyen
Author-email: hvn@familug.org
License: UNKNOWN
Project-URL: Bug Tracker, https://github.com/hvnsweeting/clista/issues
Platform: UNKNOWN
Classifier: Programming Language :: Python :: 3
Classifier: License :: OSI Approved :: MIT License
Classifier: Operating System :: OS Independent
Requires-Python: >=3.6
